matrixelement/__init__.py
matrixelement/matrixelement.py
matrixelement/qed/e_mu_e_mu/__init__.py
matrixelement/qed/e_mu_e_mu_massless/__init__.py
matrixelement/sm/__init__.py
matrixelement/sm/e_e_mu_mu/__init__.py
matrixelement-0.0.2.dist-info/LICENSE
matrixelement-0.0.2.dist-info/METADATA
matrixelement-0.0.2.dist-info/WHEEL
matrixelement-0.0.2.dist-info/RECORD
