Metadata-Version: 2.1
Name: matrixelement
Version: 0.0.2
Summary: 
Author: Alexander Puck Neuwirth
Author-email: alexander@neuwirth-informatik.de
Requires-Python: >=3.9,<4.0
Classifier: Programming Language :: Python :: 3
Classifier: Programming Language :: Python :: 3.9
Classifier: Programming Language :: Python :: 3.10
Classifier: Programming Language :: Python :: 3.11
Classifier: Programming Language :: Python :: 3.12
Provides-Extra: compute
Requires-Dist: feynamp (>=0.0.9) ; extra == "compute"
Requires-Dist: feynmodel (>=0.0.5)
Requires-Dist: jax[cpu,jaxlib] (>=0.4.26,<0.5.0)
Requires-Dist: jaxlib[cpu,tpu] (>=0.4.26,<0.5.0)
Requires-Dist: pyfeyn2 ; extra == "compute"
Requires-Dist: pyqgraf ; extra == "compute"
Requires-Dist: sympy
Requires-Dist: sympy2jax
